{
  "timestamp": "2025-07-07T00:07:15.846056",
  "query": "Godot C# strategy prototype structure",
  "context": {
    "game_type": "strategy",
    "phase": "prototype",
    "task": "create_game_loop"
  },
  "results_count": 16,
  "best_practices": [
    {
      "source": "stackoverflow",
      "title": "Godot UI Implementation",
      "relevance": 0.7221302468658255,
      "tags": [
        "godot",
        "ui",
        "interface",
        "hud"
      ],
      "has_code": true
    },
    {
      "source": "github",
      "title": "Godot UI Implementation",
      "relevance": 0.7166683889249233,
      "tags": [
        "godot",
        "ui",
        "interface",
        "hud"
      ],
      "has_code": true
    },
    {
      "source": "documentation",
      "title": "Godot UI Implementation",
      "relevance": 0.5429701442758283,
      "tags": [
        "godot",
        "ui",
        "interface",
        "hud"
      ],
      "has_code": true
    },
    {
      "source": "godot_forums",
      "title": "Godot UI Implementation",
      "relevance": 0.520377626195343,
      "tags": [
        "godot",
        "ui",
        "interface",
        "hud"
      ],
      "has_code": true
    },
    {
      "source": "documentation",
      "title": "Solution for prototype phase implementation patterns",
      "relevance": 0.42708493003308223,
      "tags": [],
      "has_code": false
    },
    {
      "source": "stackoverflow",
      "title": "Solution for strategy game development best practices",
      "relevance": 0.40207557652377485,
      "tags": [],
      "has_code": false
    },
    {
      "source": "github",
      "title": "Solution for strategy game development best practices",
      "relevance": 0.3968082709286978,
      "tags": [],
      "has_code": false
    },
    {
      "source": "documentation",
      "title": "Solution for strategy game development best practices",
      "relevance": 0.3966132912622769,
      "tags": [],
      "has_code": false
    },
    {
      "source": "github",
      "title": "Solution for avoid common mistakes strategy development",
      "relevance": 0.3333873444678423,
      "tags": [],
      "has_code": false
    },
    {
      "source": "godot_forums",
      "title": "Solution for prototype phase implementation patterns",
      "relevance": 0.3325442590202299,
      "tags": [],
      "has_code": false
    },
    {
      "source": "github",
      "title": "Solution for prototype phase implementation patterns",
      "relevance": 0.3219928771935492,
      "tags": [],
      "has_code": false
    },
    {
      "source": "documentation",
      "title": "Solution for avoid common mistakes strategy development",
      "relevance": 0.30041750109313814,
      "tags": [],
      "has_code": false
    },
    {
      "source": "stackoverflow",
      "title": "Solution for prototype phase implementation patterns",
      "relevance": 0.2957347625601348,
      "tags": [],
      "has_code": false
    },
    {
      "source": "stackoverflow",
      "title": "Solution for avoid common mistakes strategy development",
      "relevance": 0.2846581155706302,
      "tags": [],
      "has_code": false
    },
    {
      "source": "godot_forums",
      "title": "Solution for strategy game development best practices",
      "relevance": 0.27037189206913326,
      "tags": [],
      "has_code": false
    },
    {
      "source": "godot_forums",
      "title": "Solution for avoid common mistakes strategy development",
      "relevance": 0.2354250924515235,
      "tags": [],
      "has_code": false
    }
  ]
}