{
  "timestamp": "2025-07-07T01:23:49.747253",
  "query": "Godot C# strategy prototype structure",
  "context": {
    "game_type": "strategy",
    "phase": "prototype",
    "task": "create_game_loop"
  },
  "results_count": 16,
  "best_practices": [
    {
      "source": "stackoverflow",
      "title": "Godot UI Implementation",
      "relevance": 0.6672695067296261,
      "tags": [
        "godot",
        "ui",
        "interface",
        "hud"
      ],
      "has_code": true
    },
    {
      "source": "godot_forums",
      "title": "Godot UI Implementation",
      "relevance": 0.6110188647755698,
      "tags": [
        "godot",
        "ui",
        "interface",
        "hud"
      ],
      "has_code": true
    },
    {
      "source": "documentation",
      "title": "Godot UI Implementation",
      "relevance": 0.6095973048998066,
      "tags": [
        "godot",
        "ui",
        "interface",
        "hud"
      ],
      "has_code": true
    },
    {
      "source": "github",
      "title": "Godot UI Implementation",
      "relevance": 0.488861950867181,
      "tags": [
        "godot",
        "ui",
        "interface",
        "hud"
      ],
      "has_code": true
    },
    {
      "source": "documentation",
      "title": "Solution for prototype phase implementation patterns",
      "relevance": 0.4185591144545422,
      "tags": [],
      "has_code": false
    },
    {
      "source": "documentation",
      "title": "Solution for avoid common mistakes strategy development",
      "relevance": 0.41251451323299626,
      "tags": [],
      "has_code": false
    },
    {
      "source": "github",
      "title": "Solution for strategy game development best practices",
      "relevance": 0.3899186646638096,
      "tags": [],
      "has_code": false
    },
    {
      "source": "godot_forums",
      "title": "Solution for avoid common mistakes strategy development",
      "relevance": 0.3695229078466215,
      "tags": [],
      "has_code": false
    },
    {
      "source": "documentation",
      "title": "Solution for strategy game development best practices",
      "relevance": 0.36802151942796807,
      "tags": [],
      "has_code": false
    },
    {
      "source": "stackoverflow",
      "title": "Solution for avoid common mistakes strategy development",
      "relevance": 0.33099046863767395,
      "tags": [],
      "has_code": false
    },
    {
      "source": "github",
      "title": "Solution for prototype phase implementation patterns",
      "relevance": 0.32757059792866805,
      "tags": [],
      "has_code": false
    },
    {
      "source": "godot_forums",
      "title": "Solution for prototype phase implementation patterns",
      "relevance": 0.3250204248756083,
      "tags": [],
      "has_code": false
    },
    {
      "source": "stackoverflow",
      "title": "Solution for strategy game development best practices",
      "relevance": 0.3174957208636883,
      "tags": [],
      "has_code": false
    },
    {
      "source": "stackoverflow",
      "title": "Solution for prototype phase implementation patterns",
      "relevance": 0.3166475531527899,
      "tags": [],
      "has_code": false
    },
    {
      "source": "github",
      "title": "Solution for avoid common mistakes strategy development",
      "relevance": 0.278771740871823,
      "tags": [],
      "has_code": false
    },
    {
      "source": "godot_forums",
      "title": "Solution for strategy game development best practices",
      "relevance": 0.2576864787845806,
      "tags": [],
      "has_code": false
    }
  ]
}