{
  "timestamp": "2025-07-06T22:30:08.061584",
  "query": "Godot C# strategy prototype structure",
  "context": {
    "game_type": "strategy",
    "phase": "prototype",
    "task": "create_game_loop"
  },
  "results_count": 16,
  "best_practices": [
    {
      "source": "documentation",
      "title": "Godot UI Implementation",
      "relevance": 0.8287091106939558,
      "tags": [
        "godot",
        "ui",
        "interface",
        "hud"
      ],
      "has_code": true
    },
    {
      "source": "github",
      "title": "Godot UI Implementation",
      "relevance": 0.7015014983788701,
      "tags": [
        "godot",
        "ui",
        "interface",
        "hud"
      ],
      "has_code": true
    },
    {
      "source": "godot_forums",
      "title": "Godot UI Implementation",
      "relevance": 0.5911292286740251,
      "tags": [
        "godot",
        "ui",
        "interface",
        "hud"
      ],
      "has_code": true
    },
    {
      "source": "stackoverflow",
      "title": "Godot UI Implementation",
      "relevance": 0.5112175074226661,
      "tags": [
        "godot",
        "ui",
        "interface",
        "hud"
      ],
      "has_code": true
    },
    {
      "source": "documentation",
      "title": "Solution for avoid common mistakes strategy development",
      "relevance": 0.42854188806327026,
      "tags": [],
      "has_code": false
    },
    {
      "source": "github",
      "title": "Solution for strategy game development best practices",
      "relevance": 0.3727499487685327,
      "tags": [],
      "has_code": false
    },
    {
      "source": "stackoverflow",
      "title": "Solution for strategy game development best practices",
      "relevance": 0.3693098894703349,
      "tags": [],
      "has_code": false
    },
    {
      "source": "stackoverflow",
      "title": "Solution for avoid common mistakes strategy development",
      "relevance": 0.35886037327229564,
      "tags": [],
      "has_code": false
    },
    {
      "source": "documentation",
      "title": "Solution for prototype phase implementation patterns",
      "relevance": 0.3578715535623336,
      "tags": [],
      "has_code": false
    },
    {
      "source": "stackoverflow",
      "title": "Solution for prototype phase implementation patterns",
      "relevance": 0.3420741700550779,
      "tags": [],
      "has_code": false
    },
    {
      "source": "godot_forums",
      "title": "Solution for strategy game development best practices",
      "relevance": 0.3395013460741645,
      "tags": [],
      "has_code": false
    },
    {
      "source": "documentation",
      "title": "Solution for strategy game development best practices",
      "relevance": 0.3219608757961135,
      "tags": [],
      "has_code": false
    },
    {
      "source": "godot_forums",
      "title": "Solution for avoid common mistakes strategy development",
      "relevance": 0.3128241786196747,
      "tags": [],
      "has_code": false
    },
    {
      "source": "github",
      "title": "Solution for avoid common mistakes strategy development",
      "relevance": 0.3005554794903977,
      "tags": [],
      "has_code": false
    },
    {
      "source": "github",
      "title": "Solution for prototype phase implementation patterns",
      "relevance": 0.24697663435970196,
      "tags": [],
      "has_code": false
    },
    {
      "source": "godot_forums",
      "title": "Solution for prototype phase implementation patterns",
      "relevance": 0.24419597332062104,
      "tags": [],
      "has_code": false
    }
  ]
}