{
  "timestamp": "2025-07-07T01:30:10.124413",
  "query": "Godot C# strategy prototype structure",
  "context": {
    "game_type": "strategy",
    "phase": "prototype",
    "task": "create_game_loop"
  },
  "results_count": 16,
  "best_practices": [
    {
      "source": "documentation",
      "title": "Godot UI Implementation",
      "relevance": 0.6061540474062311,
      "tags": [
        "godot",
        "ui",
        "interface",
        "hud"
      ],
      "has_code": true
    },
    {
      "source": "stackoverflow",
      "title": "Godot UI Implementation",
      "relevance": 0.5553951330574565,
      "tags": [
        "godot",
        "ui",
        "interface",
        "hud"
      ],
      "has_code": true
    },
    {
      "source": "godot_forums",
      "title": "Godot UI Implementation",
      "relevance": 0.5471648556303348,
      "tags": [
        "godot",
        "ui",
        "interface",
        "hud"
      ],
      "has_code": true
    },
    {
      "source": "github",
      "title": "Godot UI Implementation",
      "relevance": 0.5204089432151853,
      "tags": [
        "godot",
        "ui",
        "interface",
        "hud"
      ],
      "has_code": true
    },
    {
      "source": "documentation",
      "title": "Solution for avoid common mistakes strategy development",
      "relevance": 0.41490610432933145,
      "tags": [],
      "has_code": false
    },
    {
      "source": "documentation",
      "title": "Solution for strategy game development best practices",
      "relevance": 0.4018037151931375,
      "tags": [],
      "has_code": false
    },
    {
      "source": "documentation",
      "title": "Solution for prototype phase implementation patterns",
      "relevance": 0.3975864648203281,
      "tags": [],
      "has_code": false
    },
    {
      "source": "stackoverflow",
      "title": "Solution for strategy game development best practices",
      "relevance": 0.3781957174703247,
      "tags": [],
      "has_code": false
    },
    {
      "source": "github",
      "title": "Solution for avoid common mistakes strategy development",
      "relevance": 0.34472154169649133,
      "tags": [],
      "has_code": false
    },
    {
      "source": "godot_forums",
      "title": "Solution for strategy game development best practices",
      "relevance": 0.3244159608434203,
      "tags": [],
      "has_code": false
    },
    {
      "source": "stackoverflow",
      "title": "Solution for avoid common mistakes strategy development",
      "relevance": 0.31401729673170314,
      "tags": [],
      "has_code": false
    },
    {
      "source": "github",
      "title": "Solution for strategy game development best practices",
      "relevance": 0.2839373103819228,
      "tags": [],
      "has_code": false
    },
    {
      "source": "github",
      "title": "Solution for prototype phase implementation patterns",
      "relevance": 0.283396774116589,
      "tags": [],
      "has_code": false
    },
    {
      "source": "godot_forums",
      "title": "Solution for prototype phase implementation patterns",
      "relevance": 0.26302002614663933,
      "tags": [],
      "has_code": false
    },
    {
      "source": "stackoverflow",
      "title": "Solution for prototype phase implementation patterns",
      "relevance": 0.26071521736820946,
      "tags": [],
      "has_code": false
    },
    {
      "source": "godot_forums",
      "title": "Solution for avoid common mistakes strategy development",
      "relevance": 0.23599432717442353,
      "tags": [],
      "has_code": false
    }
  ]
}