{
  "timestamp": "2025-07-06T23:04:07.805842",
  "query": "Godot C# strategy prototype structure",
  "context": {
    "game_type": "strategy",
    "phase": "prototype",
    "task": "create_game_loop"
  },
  "results_count": 16,
  "best_practices": [
    {
      "source": "github",
      "title": "Godot UI Implementation",
      "relevance": 0.7820089712776266,
      "tags": [
        "godot",
        "ui",
        "interface",
        "hud"
      ],
      "has_code": true
    },
    {
      "source": "godot_forums",
      "title": "Godot UI Implementation",
      "relevance": 0.7156302754781909,
      "tags": [
        "godot",
        "ui",
        "interface",
        "hud"
      ],
      "has_code": true
    },
    {
      "source": "stackoverflow",
      "title": "Godot UI Implementation",
      "relevance": 0.6302533661449962,
      "tags": [
        "godot",
        "ui",
        "interface",
        "hud"
      ],
      "has_code": true
    },
    {
      "source": "documentation",
      "title": "Godot UI Implementation",
      "relevance": 0.5799923595846747,
      "tags": [
        "godot",
        "ui",
        "interface",
        "hud"
      ],
      "has_code": true
    },
    {
      "source": "documentation",
      "title": "Solution for avoid common mistakes strategy development",
      "relevance": 0.438446926641697,
      "tags": [],
      "has_code": false
    },
    {
      "source": "stackoverflow",
      "title": "Solution for strategy game development best practices",
      "relevance": 0.42405940851842794,
      "tags": [],
      "has_code": false
    },
    {
      "source": "documentation",
      "title": "Solution for prototype phase implementation patterns",
      "relevance": 0.39530017343322477,
      "tags": [],
      "has_code": false
    },
    {
      "source": "stackoverflow",
      "title": "Solution for avoid common mistakes strategy development",
      "relevance": 0.3556360071576379,
      "tags": [],
      "has_code": false
    },
    {
      "source": "godot_forums",
      "title": "Solution for avoid common mistakes strategy development",
      "relevance": 0.3404082734702163,
      "tags": [],
      "has_code": false
    },
    {
      "source": "godot_forums",
      "title": "Solution for prototype phase implementation patterns",
      "relevance": 0.32733669812886385,
      "tags": [],
      "has_code": false
    },
    {
      "source": "github",
      "title": "Solution for avoid common mistakes strategy development",
      "relevance": 0.3218154845732032,
      "tags": [],
      "has_code": false
    },
    {
      "source": "stackoverflow",
      "title": "Solution for prototype phase implementation patterns",
      "relevance": 0.3126273545311698,
      "tags": [],
      "has_code": false
    },
    {
      "source": "github",
      "title": "Solution for strategy game development best practices",
      "relevance": 0.300288287009595,
      "tags": [],
      "has_code": false
    },
    {
      "source": "godot_forums",
      "title": "Solution for strategy game development best practices",
      "relevance": 0.28790034316882673,
      "tags": [],
      "has_code": false
    },
    {
      "source": "documentation",
      "title": "Solution for strategy game development best practices",
      "relevance": 0.2870488856694986,
      "tags": [],
      "has_code": false
    },
    {
      "source": "github",
      "title": "Solution for prototype phase implementation patterns",
      "relevance": 0.24511879441991558,
      "tags": [],
      "has_code": false
    }
  ]
}