{
  "timestamp": "2025-07-06T06:34:50.327443",
  "query": "Godot C# rpg prototype structure",
  "context": {
    "game_type": "rpg",
    "phase": "prototype",
    "task": "create_game_loop"
  },
  "results_count": 16,
  "best_practices": [
    {
      "source": "stackoverflow",
      "title": "Godot UI Implementation",
      "relevance": 0.8497723268093471,
      "tags": [
        "godot",
        "ui",
        "interface",
        "hud"
      ],
      "has_code": true
    },
    {
      "source": "documentation",
      "title": "Godot UI Implementation",
      "relevance": 0.8012476221906257,
      "tags": [
        "godot",
        "ui",
        "interface",
        "hud"
      ],
      "has_code": true
    },
    {
      "source": "github",
      "title": "Godot UI Implementation",
      "relevance": 0.6497812327750085,
      "tags": [
        "godot",
        "ui",
        "interface",
        "hud"
      ],
      "has_code": true
    },
    {
      "source": "godot_forums",
      "title": "Godot UI Implementation",
      "relevance": 0.4559036595078899,
      "tags": [
        "godot",
        "ui",
        "interface",
        "hud"
      ],
      "has_code": true
    },
    {
      "source": "documentation",
      "title": "Solution for rpg game development best practices",
      "relevance": 0.40156178680103843,
      "tags": [],
      "has_code": false
    },
    {
      "source": "stackoverflow",
      "title": "Solution for rpg game development best practices",
      "relevance": 0.3975265754426649,
      "tags": [],
      "has_code": false
    },
    {
      "source": "github",
      "title": "Solution for prototype phase implementation patterns",
      "relevance": 0.3952481258763696,
      "tags": [],
      "has_code": false
    },
    {
      "source": "godot_forums",
      "title": "Solution for rpg game development best practices",
      "relevance": 0.35916493734593236,
      "tags": [],
      "has_code": false
    },
    {
      "source": "documentation",
      "title": "Solution for prototype phase implementation patterns",
      "relevance": 0.3578757827690471,
      "tags": [],
      "has_code": false
    },
    {
      "source": "github",
      "title": "Solution for avoid common mistakes rpg development",
      "relevance": 0.3551667453956029,
      "tags": [],
      "has_code": false
    },
    {
      "source": "godot_forums",
      "title": "Solution for prototype phase implementation patterns",
      "relevance": 0.34817443741181453,
      "tags": [],
      "has_code": false
    },
    {
      "source": "github",
      "title": "Solution for rpg game development best practices",
      "relevance": 0.32214323765608044,
      "tags": [],
      "has_code": false
    },
    {
      "source": "documentation",
      "title": "Solution for avoid common mistakes rpg development",
      "relevance": 0.3113097070960218,
      "tags": [],
      "has_code": false
    },
    {
      "source": "stackoverflow",
      "title": "Solution for prototype phase implementation patterns",
      "relevance": 0.2862717915839691,
      "tags": [],
      "has_code": false
    },
    {
      "source": "stackoverflow",
      "title": "Solution for avoid common mistakes rpg development",
      "relevance": 0.25831083530442617,
      "tags": [],
      "has_code": false
    },
    {
      "source": "godot_forums",
      "title": "Solution for avoid common mistakes rpg development",
      "relevance": 0.2553429364679315,
      "tags": [],
      "has_code": false
    }
  ]
}