{
  "timestamp": "2025-07-06T05:28:21.220837",
  "query": "Panda3D rpg prototype structure",
  "context": {
    "game_type": "rpg",
    "phase": "prototype",
    "task": "create_game_loop"
  },
  "results_count": 16,
  "best_practices": [
    {
      "source": "documentation",
      "title": "Godot UI Implementation",
      "relevance": 0.8427300450783497,
      "tags": [
        "godot",
        "ui",
        "interface",
        "hud"
      ],
      "has_code": true
    },
    {
      "source": "stackoverflow",
      "title": "Godot UI Implementation",
      "relevance": 0.7786896294183656,
      "tags": [
        "godot",
        "ui",
        "interface",
        "hud"
      ],
      "has_code": true
    },
    {
      "source": "godot_forums",
      "title": "Godot UI Implementation",
      "relevance": 0.7188386203310803,
      "tags": [
        "godot",
        "ui",
        "interface",
        "hud"
      ],
      "has_code": true
    },
    {
      "source": "github",
      "title": "Godot UI Implementation",
      "relevance": 0.7127277148715558,
      "tags": [
        "godot",
        "ui",
        "interface",
        "hud"
      ],
      "has_code": true
    },
    {
      "source": "github",
      "title": "Solution for avoid common mistakes rpg development",
      "relevance": 0.39727563421878714,
      "tags": [],
      "has_code": false
    },
    {
      "source": "documentation",
      "title": "Solution for avoid common mistakes rpg development",
      "relevance": 0.38562076978982357,
      "tags": [],
      "has_code": false
    },
    {
      "source": "stackoverflow",
      "title": "Solution for prototype phase implementation patterns",
      "relevance": 0.3766195852113458,
      "tags": [],
      "has_code": false
    },
    {
      "source": "documentation",
      "title": "Solution for prototype phase implementation patterns",
      "relevance": 0.3747719503791953,
      "tags": [],
      "has_code": false
    },
    {
      "source": "github",
      "title": "Solution for rpg game development best practices",
      "relevance": 0.3651024155362436,
      "tags": [],
      "has_code": false
    },
    {
      "source": "stackoverflow",
      "title": "Solution for rpg game development best practices",
      "relevance": 0.3419926438943472,
      "tags": [],
      "has_code": false
    },
    {
      "source": "documentation",
      "title": "Solution for rpg game development best practices",
      "relevance": 0.3360197663672458,
      "tags": [],
      "has_code": false
    },
    {
      "source": "godot_forums",
      "title": "Solution for prototype phase implementation patterns",
      "relevance": 0.310996497397429,
      "tags": [],
      "has_code": false
    },
    {
      "source": "stackoverflow",
      "title": "Solution for avoid common mistakes rpg development",
      "relevance": 0.2943682435896907,
      "tags": [],
      "has_code": false
    },
    {
      "source": "github",
      "title": "Solution for prototype phase implementation patterns",
      "relevance": 0.2897040342935231,
      "tags": [],
      "has_code": false
    },
    {
      "source": "godot_forums",
      "title": "Solution for avoid common mistakes rpg development",
      "relevance": 0.2739844955376807,
      "tags": [],
      "has_code": false
    },
    {
      "source": "godot_forums",
      "title": "Solution for rpg game development best practices",
      "relevance": 0.2464272445813956,
      "tags": [],
      "has_code": false
    }
  ]
}