{
  "timestamp": "2025-07-06T05:07:25.561329",
  "query": "Panda3D rpg prototype structure",
  "context": {
    "game_type": "rpg",
    "phase": "prototype",
    "task": "create_game_loop"
  },
  "results_count": 16,
  "best_practices": [
    {
      "source": "stackoverflow",
      "title": "Godot UI Implementation",
      "relevance": 0.7334814554497314,
      "tags": [
        "godot",
        "ui",
        "interface",
        "hud"
      ],
      "has_code": true
    },
    {
      "source": "documentation",
      "title": "Godot UI Implementation",
      "relevance": 0.7048255417390635,
      "tags": [
        "godot",
        "ui",
        "interface",
        "hud"
      ],
      "has_code": true
    },
    {
      "source": "github",
      "title": "Godot UI Implementation",
      "relevance": 0.6660040060990423,
      "tags": [
        "godot",
        "ui",
        "interface",
        "hud"
      ],
      "has_code": true
    },
    {
      "source": "godot_forums",
      "title": "Godot UI Implementation",
      "relevance": 0.5199797503935406,
      "tags": [
        "godot",
        "ui",
        "interface",
        "hud"
      ],
      "has_code": true
    },
    {
      "source": "documentation",
      "title": "Solution for avoid common mistakes rpg development",
      "relevance": 0.439852338941177,
      "tags": [],
      "has_code": false
    },
    {
      "source": "documentation",
      "title": "Solution for prototype phase implementation patterns",
      "relevance": 0.41007541990962054,
      "tags": [],
      "has_code": false
    },
    {
      "source": "stackoverflow",
      "title": "Solution for avoid common mistakes rpg development",
      "relevance": 0.3677622437226924,
      "tags": [],
      "has_code": false
    },
    {
      "source": "github",
      "title": "Solution for avoid common mistakes rpg development",
      "relevance": 0.35440259885036973,
      "tags": [],
      "has_code": false
    },
    {
      "source": "github",
      "title": "Solution for prototype phase implementation patterns",
      "relevance": 0.3528350150730741,
      "tags": [],
      "has_code": false
    },
    {
      "source": "stackoverflow",
      "title": "Solution for rpg game development best practices",
      "relevance": 0.30826685324398473,
      "tags": [],
      "has_code": false
    },
    {
      "source": "stackoverflow",
      "title": "Solution for prototype phase implementation patterns",
      "relevance": 0.3018941353650087,
      "tags": [],
      "has_code": false
    },
    {
      "source": "godot_forums",
      "title": "Solution for rpg game development best practices",
      "relevance": 0.29486071889883064,
      "tags": [],
      "has_code": false
    },
    {
      "source": "documentation",
      "title": "Solution for rpg game development best practices",
      "relevance": 0.2854647658855745,
      "tags": [],
      "has_code": false
    },
    {
      "source": "godot_forums",
      "title": "Solution for prototype phase implementation patterns",
      "relevance": 0.27153131980046963,
      "tags": [],
      "has_code": false
    },
    {
      "source": "github",
      "title": "Solution for rpg game development best practices",
      "relevance": 0.270373468418888,
      "tags": [],
      "has_code": false
    },
    {
      "source": "godot_forums",
      "title": "Solution for avoid common mistakes rpg development",
      "relevance": 0.23931747207392468,
      "tags": [],
      "has_code": false
    }
  ]
}