{
  "timestamp": "2025-07-06T06:42:13.232881",
  "query": "Godot C# rpg prototype structure",
  "context": {
    "game_type": "rpg",
    "phase": "prototype",
    "task": "create_game_loop"
  },
  "results_count": 16,
  "best_practices": [
    {
      "source": "documentation",
      "title": "Godot UI Implementation",
      "relevance": 0.7190265417476405,
      "tags": [
        "godot",
        "ui",
        "interface",
        "hud"
      ],
      "has_code": true
    },
    {
      "source": "stackoverflow",
      "title": "Godot UI Implementation",
      "relevance": 0.6379135603568864,
      "tags": [
        "godot",
        "ui",
        "interface",
        "hud"
      ],
      "has_code": true
    },
    {
      "source": "github",
      "title": "Godot UI Implementation",
      "relevance": 0.5925482025214595,
      "tags": [
        "godot",
        "ui",
        "interface",
        "hud"
      ],
      "has_code": true
    },
    {
      "source": "godot_forums",
      "title": "Godot UI Implementation",
      "relevance": 0.45175570209281035,
      "tags": [
        "godot",
        "ui",
        "interface",
        "hud"
      ],
      "has_code": true
    },
    {
      "source": "documentation",
      "title": "Solution for prototype phase implementation patterns",
      "relevance": 0.44768833040605205,
      "tags": [],
      "has_code": false
    },
    {
      "source": "documentation",
      "title": "Solution for avoid common mistakes rpg development",
      "relevance": 0.4369015201775348,
      "tags": [],
      "has_code": false
    },
    {
      "source": "stackoverflow",
      "title": "Solution for prototype phase implementation patterns",
      "relevance": 0.4218041208334199,
      "tags": [],
      "has_code": false
    },
    {
      "source": "github",
      "title": "Solution for rpg game development best practices",
      "relevance": 0.39754010705599896,
      "tags": [],
      "has_code": false
    },
    {
      "source": "stackoverflow",
      "title": "Solution for rpg game development best practices",
      "relevance": 0.35675883903413547,
      "tags": [],
      "has_code": false
    },
    {
      "source": "documentation",
      "title": "Solution for rpg game development best practices",
      "relevance": 0.3516604453069653,
      "tags": [],
      "has_code": false
    },
    {
      "source": "stackoverflow",
      "title": "Solution for avoid common mistakes rpg development",
      "relevance": 0.3371345527670032,
      "tags": [],
      "has_code": false
    },
    {
      "source": "godot_forums",
      "title": "Solution for prototype phase implementation patterns",
      "relevance": 0.32370224302737016,
      "tags": [],
      "has_code": false
    },
    {
      "source": "godot_forums",
      "title": "Solution for avoid common mistakes rpg development",
      "relevance": 0.28550004537301543,
      "tags": [],
      "has_code": false
    },
    {
      "source": "github",
      "title": "Solution for avoid common mistakes rpg development",
      "relevance": 0.2756721874623666,
      "tags": [],
      "has_code": false
    },
    {
      "source": "godot_forums",
      "title": "Solution for rpg game development best practices",
      "relevance": 0.24739485757181257,
      "tags": [],
      "has_code": false
    },
    {
      "source": "github",
      "title": "Solution for prototype phase implementation patterns",
      "relevance": 0.2420592079569615,
      "tags": [],
      "has_code": false
    }
  ]
}