{
  "timestamp": "2025-07-06T08:21:05.549248",
  "query": "Godot C# rpg prototype structure",
  "context": {
    "game_type": "rpg",
    "phase": "prototype",
    "task": "create_game_loop"
  },
  "results_count": 16,
  "best_practices": [
    {
      "source": "documentation",
      "title": "Godot UI Implementation",
      "relevance": 0.8540306790408466,
      "tags": [
        "godot",
        "ui",
        "interface",
        "hud"
      ],
      "has_code": true
    },
    {
      "source": "stackoverflow",
      "title": "Godot UI Implementation",
      "relevance": 0.6194259355982136,
      "tags": [
        "godot",
        "ui",
        "interface",
        "hud"
      ],
      "has_code": true
    },
    {
      "source": "godot_forums",
      "title": "Godot UI Implementation",
      "relevance": 0.49510545033588804,
      "tags": [
        "godot",
        "ui",
        "interface",
        "hud"
      ],
      "has_code": true
    },
    {
      "source": "github",
      "title": "Godot UI Implementation",
      "relevance": 0.4905994066885373,
      "tags": [
        "godot",
        "ui",
        "interface",
        "hud"
      ],
      "has_code": true
    },
    {
      "source": "stackoverflow",
      "title": "Solution for rpg game development best practices",
      "relevance": 0.4218686287169241,
      "tags": [],
      "has_code": false
    },
    {
      "source": "github",
      "title": "Solution for prototype phase implementation patterns",
      "relevance": 0.3782522298664863,
      "tags": [],
      "has_code": false
    },
    {
      "source": "github",
      "title": "Solution for avoid common mistakes rpg development",
      "relevance": 0.3498029646169054,
      "tags": [],
      "has_code": false
    },
    {
      "source": "stackoverflow",
      "title": "Solution for avoid common mistakes rpg development",
      "relevance": 0.3384291086186624,
      "tags": [],
      "has_code": false
    },
    {
      "source": "stackoverflow",
      "title": "Solution for prototype phase implementation patterns",
      "relevance": 0.3312258929856829,
      "tags": [],
      "has_code": false
    },
    {
      "source": "documentation",
      "title": "Solution for rpg game development best practices",
      "relevance": 0.3252833279449499,
      "tags": [],
      "has_code": false
    },
    {
      "source": "github",
      "title": "Solution for rpg game development best practices",
      "relevance": 0.3252238160920066,
      "tags": [],
      "has_code": false
    },
    {
      "source": "documentation",
      "title": "Solution for avoid common mistakes rpg development",
      "relevance": 0.3132864559112879,
      "tags": [],
      "has_code": false
    },
    {
      "source": "godot_forums",
      "title": "Solution for prototype phase implementation patterns",
      "relevance": 0.29953782173636473,
      "tags": [],
      "has_code": false
    },
    {
      "source": "godot_forums",
      "title": "Solution for rpg game development best practices",
      "relevance": 0.2994124530205334,
      "tags": [],
      "has_code": false
    },
    {
      "source": "documentation",
      "title": "Solution for prototype phase implementation patterns",
      "relevance": 0.271457737015056,
      "tags": [],
      "has_code": false
    },
    {
      "source": "godot_forums",
      "title": "Solution for avoid common mistakes rpg development",
      "relevance": 0.2445079457493307,
      "tags": [],
      "has_code": false
    }
  ]
}